nicks_plot_utils/Hist1D.py
nicks_plot_utils/Hist2D.py
nicks_plot_utils/Rhist.py
nicks_plot_utils/Scatter.py
nicks_plot_utils/__init__.py
nicks_plot_utils-1.1.dist-info/LICENSE
nicks_plot_utils-1.1.dist-info/METADATA
nicks_plot_utils-1.1.dist-info/WHEEL
nicks_plot_utils-1.1.dist-info/top_level.txt
nicks_plot_utils-1.1.dist-info/RECORD
