Metadata-Version: 2.1
Name: nicks-plot-utils
Version: 1.1
Summary: A example Python package
Home-page: https://github.com/tylern4/nicks_plot_utils
Author: Nick Tyler
Author-email: nicholas.s.tyler.4@gmail.com
License: BSD 2-clause
Classifier: Development Status :: 1 - Planning
Classifier: Intended Audience :: Science/Research
Classifier: License :: OSI Approved :: BSD License
Classifier: Operating System :: POSIX :: Linux
Classifier: Programming Language :: Python :: 3.5
Classifier: Programming Language :: Python :: 3.7
Classifier: Programming Language :: Python :: 3.8
Classifier: Programming Language :: Python :: 3.9
Requires-Python: >=3.5
License-File: LICENSE
Requires-Dist: matplotlib
Requires-Dist: numpy
Requires-Dist: boost-histogram
Requires-Dist: scipy
Requires-Dist: lmfit
